fwissr
