Metadata-Version: 1.1
Name: fwissr
Version: 1.0.4
Summary: fwissr is a registry configuration tool.
Home-page: https://github.com/fotonauts/fwissr-python
Author: Pierre Baillet
Author-email: pierre@baillet.name
License: MIT
Keywords: fwissr
Platform: UNKNOWN
Classifier: Intended Audience :: Developers
Classifier: License :: OSI Approved :: MIT License
Classifier: Programming Language :: Python :: 2
Classifier: Programming Language :: Python :: 2.6
Classifier: Programming Language :: Python :: 2.7
